msi_recal/__init__.py
msi_recal/__main__.py
msi_recal/db_peak_match.py
msi_recal/evaluate.py
msi_recal/join_by_mz.py
msi_recal/math.py
msi_recal/mean_spectrum.py
msi_recal/mx_warp_peaks.py
msi_recal/params.py
msi_recal/plot.py
msi_recal/recalibrate.py
msi_recal/dbs/CoreMetabolome-v3.csv
msi_recal/dbs/HMDB-v4.csv
msi_recal/dbs/matrix_9aa_neg.csv
msi_recal/dbs/matrix_chca_pos.csv
msi_recal/dbs/matrix_dan_neg.csv
msi_recal/dbs/matrix_dan_pos.csv
msi_recal/dbs/matrix_dctb_pos.csv
msi_recal/dbs/matrix_dhap_neg.csv
msi_recal/dbs/matrix_dhap_pos.csv
msi_recal/dbs/matrix_dhb_neg.csv
msi_recal/dbs/matrix_dhb_pos.csv
msi_recal/dbs/matrix_nor_neg.csv
msi_recal/dbs/matrix_nor_pos.csv
msi_recal/dbs/matrix_pna_neg.csv
msi_recal/dbs/matrix_pna_pos.csv
msi_recal/dbs/matrix_thap_neg.csv
msi_recal/passes/__init__.py
msi_recal/passes/align_msiwarp.py
msi_recal/passes/align_ransac.py
msi_recal/passes/normalize.py
msi_recal/passes/recal_msiwarp.py
msi_recal/passes/recal_ransac.py
msi_recal/passes/transform.py
msiwarp/__init__.py
msiwarp/msiwarp.cp37-win_amd64.pyd
msiwarp/util/__init__.py
msiwarp/util/parabolic_centroid.py
msiwarp/util/read_sbd.py
msiwarp/util/warp.py
msi_recal-0.2.3.dist-info/METADATA
msi_recal-0.2.3.dist-info/WHEEL
msi_recal-0.2.3.dist-info/top_level.txt
msi_recal-0.2.3.dist-info/RECORD
